IPYNBrenderer033/__init__.py
IPYNBrenderer033/custom_exception.py
IPYNBrenderer033/logger.py
IPYNBrenderer033/website.py
IPYNBrenderer033/youtube.py
IPYNBrenderer033-0.0.2.dist-info/LICENSE
IPYNBrenderer033-0.0.2.dist-info/METADATA
IPYNBrenderer033-0.0.2.dist-info/WHEEL
IPYNBrenderer033-0.0.2.dist-info/top_level.txt
IPYNBrenderer033-0.0.2.dist-info/RECORD
