Metadata-Version: 2.1
Name: IPYNBrenderer033
Version: 0.0.2
Summary: A small python package
Home-page: https://github.com/Dharmateja033/IPYNBrenderer033
Author: Dharmateja033
Author-email: dharmateja.2660@gmail.com
License: MIT
Project-URL: bugTracker, https://github.com/Dharmateja033/IPYNBrenderer033/issues
Classifier: Programming Language :: Python :: 3.12
Classifier: Operating System :: OS Independent
Requires-Python: >=3.11
License-File: LICENSE
Requires-Dist: ensure
Requires-Dist: py-youtube
Provides-Extra: testing
Requires-Dist: pytest >=7.1.3 ; extra == 'testing'
Requires-Dist: mypy >=0.971 ; extra == 'testing'
Requires-Dist: flake8 >=5.0.4 ; extra == 'testing'
Requires-Dist: tox >=3.25.1 ; extra == 'testing'
Requires-Dist: black >=22.8.0 ; extra == 'testing'
